CONTRIBUTING.md
LICENSE
MANIFEST.in
README.md
setup.py
komora_service_path_plugin/__init__.py
komora_service_path_plugin/navigation.py
komora_service_path_plugin/search.py
komora_service_path_plugin/template_content.py
komora_service_path_plugin/urls.py
komora_service_path_plugin/version.py
komora_service_path_plugin.egg-info/PKG-INFO
komora_service_path_plugin.egg-info/SOURCES.txt
komora_service_path_plugin.egg-info/dependency_links.txt
komora_service_path_plugin.egg-info/not-zip-safe
komora_service_path_plugin.egg-info/top_level.txt
komora_service_path_plugin/api/__init__.py
komora_service_path_plugin/api/urls.py
komora_service_path_plugin/api/serializers/__init__.py
komora_service_path_plugin/api/serializers/segment.py
komora_service_path_plugin/api/serializers/segment_circuit_mapping.py
komora_service_path_plugin/api/serializers/service_path.py
komora_service_path_plugin/api/serializers/service_path_segment_mapping.py
komora_service_path_plugin/api/views/__init__.py
komora_service_path_plugin/api/views/segment.py
komora_service_path_plugin/api/views/segment_circuit_mapping.py
komora_service_path_plugin/api/views/service_path.py
komora_service_path_plugin/api/views/service_path_segment_mapping.py
komora_service_path_plugin/filtersets/__init__.py
komora_service_path_plugin/filtersets/segment.py
komora_service_path_plugin/filtersets/segment_circuit_mapping.py
komora_service_path_plugin/filtersets/service_path.py
komora_service_path_plugin/filtersets/service_path_segment_mapping.py
komora_service_path_plugin/forms/__init__.py
komora_service_path_plugin/forms/segment.py
komora_service_path_plugin/forms/segment_circuit_mapping.py
komora_service_path_plugin/forms/service_path.py
komora_service_path_plugin/forms/service_path_segment_mapping.py
komora_service_path_plugin/graphql/__init__.py
komora_service_path_plugin/graphql/filters.py
komora_service_path_plugin/graphql/schema.py
komora_service_path_plugin/graphql/types.py
komora_service_path_plugin/migrations/0001_segment.py
komora_service_path_plugin/migrations/0002_servicepath.py
komora_service_path_plugin/migrations/0003_servicepathsegmentmapping.py
komora_service_path_plugin/migrations/0004_add_komora_id_and_imported_data_to_models.py
