Metadata-Version: 2.1
Name: komora_service_path_plugin
Version: 1.2.7
Summary: Synchronize data between Komora and NetBox. Copies Segment and Service Paths from Komora.
Author: Jan Krupa
License: MIT
License-File: LICENSE
